glyph_media-0.5.0.dist-info/licenses/LICENSE
glyph_media_pizzalover125/__init__.py
glyph_media_pizzalover125/main.py
glyph_media-0.5.0.dist-info/METADATA
glyph_media-0.5.0.dist-info/WHEEL
glyph_media-0.5.0.dist-info/entry_points.txt
glyph_media-0.5.0.dist-info/top_level.txt
glyph_media-0.5.0.dist-info/RECORD
