Metadata-Version: 2.4
Name: glyph_media
Version: 0.5.0
Summary: A terminal-based social media.
Author-email: pizzalover125 <chessthinker600@gmail.com>
License-Expression: MIT
Project-URL: Homepage, https://glyph-sh.vercel.app/
Classifier: Programming Language :: Python :: 3
Classifier: Operating System :: OS Independent
Requires-Python: >=3.9
License-File: LICENSE
Requires-Dist: rich
Requires-Dist: questionary
Requires-Dist: requests
Dynamic: license-file
